flatten/__init__.py
flatten/cli.py
flatten_cli-1.0.1.dist-info/licenses/LICENSE
flatten_cli-1.0.1.dist-info/METADATA
flatten_cli-1.0.1.dist-info/WHEEL
flatten_cli-1.0.1.dist-info/entry_points.txt
flatten_cli-1.0.1.dist-info/top_level.txt
flatten_cli-1.0.1.dist-info/RECORD
