Metadata-Version: 2.4
Name: flatten-cli
Version: 1.0.1
Summary: A CLI tool to flatten directory structures
Home-page: https://github.com/PaxtonTerryDev/flatten
Author: PaxtonTerryDev
Author-email: PaxtonTerryDev <paxonterrydev@gmail.com>
License: MIT
Project-URL: Homepage, https://github.com/yourusername/flatten-cli
Project-URL: Repository, https://github.com/yourusername/flatten-cli
Keywords: cli,directory,flatten,filesystem,developer-tools
Classifier: Development Status :: 5 - Production/Stable
Classifier: Intended Audience :: Developers
Classifier: License :: OSI Approved :: MIT License
Classifier: Programming Language :: Python :: 3
Classifier: Operating System :: OS Independent
Classifier: Topic :: System :: Filesystems
Classifier: Topic :: Utilities
Requires-Python: >=3.7
License-File: LICENSE
Dynamic: author
Dynamic: home-page
Dynamic: license-file
Dynamic: requires-python
